criticality_score/__init__.py
criticality_score/defaults.py
criticality_score/generate.py
criticality_score/run.py
criticality_score-1.0.8.dist-info/LICENSE
criticality_score-1.0.8.dist-info/METADATA
criticality_score-1.0.8.dist-info/WHEEL
criticality_score-1.0.8.dist-info/entry_points.txt
criticality_score-1.0.8.dist-info/top_level.txt
criticality_score-1.0.8.dist-info/RECORD
