Metadata-Version: 2.1
Name: criticality-score
Version: 1.0.8
Summary: Gives criticality score for an open source project - DEPRECATED
Home-page: https://github.com/ossf/criticality-score
Author: Abhishek Arya
Author-email: 
Classifier: Programming Language :: Python :: 3
Classifier: License :: OSI Approved :: Apache Software License
Classifier: Operating System :: OS Independent
Requires-Python: >=3.6
License-File: LICENSE
Requires-Dist: PyGithub (>=1.53)
Requires-Dist: python-gitlab (>=2.5.0)
